{"openlibrary\\setup.py": {"loc": 26, "lloc": 10, "sloc": 18, "comments": 4, "multi": 0, "blank": 5, "single_comments": 3}, "openlibrary\\openlibrary\\actions.py": {"loc": 11, "lloc": 8, "sloc": 7, "comments": 0, "multi": 2, "blank": 2, "single_comments": 0}, "openlibrary\\openlibrary\\api.py": {"loc": 295, "lloc": 187, "sloc": 181, "comments": 2, "multi": 48, "blank": 61, "single_comments": 5}, "openlibrary\\openlibrary\\app.py": {"loc": 68, "lloc": 18, "sloc": 15, "comments": 10, "multi": 24, "blank": 19, "single_comments": 10}, "openlibrary\\openlibrary\\book_providers.py": {"loc": 382, "lloc": 212, "sloc": 255, "comments": 35, "multi": 13, "blank": 87, "single_comments": 27}, "openlibrary\\openlibrary\\code.py": {"loc": 69, "lloc": 37, "sloc": 46, "comments": 1, "multi": 3, "blank": 17, "single_comments": 3}, "openlibrary\\openlibrary\\config.py": {"loc": 55, "lloc": 31, "sloc": 27, "comments": 4, "multi": 13, "blank": 11, "single_comments": 4}, "openlibrary\\openlibrary\\conftest.py": {"loc": 108, "lloc": 62, "sloc": 70, "comments": 4, "multi": 2, "blank": 31, "single_comments": 5}, "openlibrary\\openlibrary\\__init__.py": {"loc": 0, "lloc": 0, "sloc": 0, "comments": 0, "multi": 0, "blank": 0, "single_comments": 0}, "openlibrary\\openlibrary\\accounts\\model.py": {"loc": 919, "lloc": 520, "sloc": 612, "comments": 54, "multi": 92, "blank": 151, "single_comments": 64}, "openlibrary\\openlibrary\\accounts\\__init__.py": {"loc": 108, "lloc": 54, "sloc": 55, "comments": 15, "multi": 13, "blank": 25, "single_comments": 15}, "openlibrary\\openlibrary\\admin\\code.py": {"loc": 33, "lloc": 20, "sloc": 20, "comments": 3, "multi": 0, "blank": 12, "single_comments": 1}, "openlibrary\\openlibrary\\admin\\numbers.py": {"loc": 254, "lloc": 141, "sloc": 160, "comments": 11, "multi": 28, "blank": 53, "single_comments": 13}, "openlibrary\\openlibrary\\admin\\stats.py": {"loc": 191, "lloc": 103, "sloc": 137, "comments": 10, "multi": 16, "blank": 30, "single_comments": 8}, "openlibrary\\openlibrary\\admin\\utils.py": {"loc": 27, "lloc": 16, "sloc": 16, "comments": 1, "multi": 2, "blank": 7, "single_comments": 2}, "openlibrary\\openlibrary\\admin\\__init__.py": {"loc": 2, "lloc": 1, "sloc": 0, "comments": 0, "multi": 2, "blank": 0, "single_comments": 0}, "openlibrary\\openlibrary\\catalog\\get_ia.py": {"loc": 106, "lloc": 70, "sloc": 65, "comments": 6, "multi": 16, "blank": 19, "single_comments": 6}, "openlibrary\\openlibrary\\catalog\\__init__.py": {"loc": 1, "lloc": 1, "sloc": 0, "comments": 0, "multi": 0, "blank": 0, "single_comments": 1}, "openlibrary\\openlibrary\\catalog\\add_book\\load_book.py": {"loc": 223, "lloc": 151, "sloc": 139, "comments": 4, "multi": 51, "blank": 30, "single_comments": 3}, "openlibrary\\openlibrary\\catalog\\add_book\\match.py": {"loc": 471, "lloc": 293, "sloc": 313, "comments": 10, "multi": 79, "blank": 73, "single_comments": 6}, "openlibrary\\openlibrary\\catalog\\add_book\\match_names.py": {"loc": 309, "lloc": 243, "sloc": 267, "comments": 7, "multi": 0, "blank": 36, "single_comments": 6}, "openlibrary\\openlibrary\\catalog\\add_book\\__init__.py": {"loc": 1054, "lloc": 565, "sloc": 638, "comments": 55, "multi": 182, "blank": 182, "single_comments": 52}, "openlibrary\\openlibrary\\catalog\\add_book\\tests\\conftest.py": {"loc": 22, "lloc": 7, "sloc": 20, "comments": 0, "multi": 0, "blank": 2, "single_comments": 0}, "openlibrary\\openlibrary\\catalog\\add_book\\tests\\test_add_book.py": {"loc": 1619, "lloc": 623, "sloc": 1383, "comments": 25, "multi": 44, "blank": 167, "single_comments": 25}, "openlibrary\\openlibrary\\catalog\\add_book\\tests\\test_load_book.py": {"loc": 67, "lloc": 36, "sloc": 51, "comments": 3, "multi": 0, "blank": 13, "single_comments": 3}, "openlibrary\\openlibrary\\catalog\\add_book\\tests\\test_match.py": {"loc": 372, "lloc": 168, "sloc": 322, "comments": 13, "multi": 0, "blank": 44, "single_comments": 6}, "openlibrary\\openlibrary\\catalog\\add_book\\tests\\test_match_names.py": {"loc": 55, "lloc": 17, "sloc": 45, "comments": 15, "multi": 0, "blank": 9, "single_comments": 1}, "openlibrary\\openlibrary\\catalog\\add_book\\tests\\__init__.py": {"loc": 0, "lloc": 0, "sloc": 0, "comments": 0, "multi": 0, "blank": 0, "single_comments": 0}, "openlibrary\\openlibrary\\catalog\\marc\\get_subjects.py": {"loc": 109, "lloc": 88, "sloc": 88, "comments": 14, "multi": 0, "blank": 16, "single_comments": 5}, "openlibrary\\openlibrary\\catalog\\marc\\html.py": {"loc": 35, "lloc": 21, "sloc": 26, "comments": 0, "multi": 0, "blank": 9, "single_comments": 0}, "openlibrary\\openlibrary\\catalog\\marc\\marc_base.py": {"loc": 102, "lloc": 74, "sloc": 71, "comments": 4, "multi": 6, "blank": 22, "single_comments": 3}, "openlibrary\\openlibrary\\catalog\\marc\\marc_binary.py": {"loc": 186, "lloc": 133, "sloc": 125, "comments": 10, "multi": 28, "blank": 24, "single_comments": 9}, "openlibrary\\openlibrary\\catalog\\marc\\marc_xml.py": {"loc": 106, "lloc": 80, "sloc": 83, "comments": 0, "multi": 0, "blank": 23, "single_comments": 0}, "openlibrary\\openlibrary\\catalog\\marc\\mnemonics.py": {"loc": 718, "lloc": 20, "sloc": 704, "comments": 2, "multi": 4, "blank": 8, "single_comments": 2}, "openlibrary\\openlibrary\\catalog\\marc\\parse.py": {"loc": 729, "lloc": 511, "sloc": 583, "comments": 64, "multi": 26, "blank": 92, "single_comments": 28}, "openlibrary\\openlibrary\\catalog\\marc\\__init__.py": {"loc": 0, "lloc": 0, "sloc": 0, "comments": 0, "multi": 0, "blank": 0, "single_comments": 0}, "openlibrary\\openlibrary\\catalog\\marc\\tests\\test_get_subjects.py": {"loc": 264, "lloc": 38, "sloc": 256, "comments": 0, "multi": 0, "blank": 8, "single_comments": 0}, "openlibrary\\openlibrary\\catalog\\marc\\tests\\test_marc.py": {"loc": 202, "lloc": 71, "sloc": 178, "comments": 8, "multi": 2, "blank": 22, "single_comments": 0}, "openlibrary\\openlibrary\\catalog\\marc\\tests\\test_marc_binary.py": {"loc": 77, "lloc": 57, "sloc": 62, "comments": 1, "multi": 3, "blank": 12, "single_comments": 0}, "openlibrary\\openlibrary\\catalog\\marc\\tests\\test_marc_html.py": {"loc": 15, "lloc": 9, "sloc": 11, "comments": 0, "multi": 0, "blank": 4, "single_comments": 0}, "openlibrary\\openlibrary\\catalog\\marc\\tests\\test_mnemonics.py": {"loc": 14, "lloc": 8, "sloc": 10, "comments": 0, "multi": 0, "blank": 4, "single_comments": 0}, "openlibrary\\openlibrary\\catalog\\marc\\tests\\test_parse.py": {"loc": 182, "lloc": 84, "sloc": 163, "comments": 10, "multi": 0, "blank": 16, "single_comments": 3}, "openlibrary\\openlibrary\\catalog\\utils\\edit.py": {"loc": 114, "lloc": 93, "sloc": 91, "comments": 1, "multi": 0, "blank": 23, "single_comments": 0}, "openlibrary\\openlibrary\\catalog\\utils\\query.py": {"loc": 182, "lloc": 140, "sloc": 144, "comments": 2, "multi": 0, "blank": 37, "single_comments": 1}, "openlibrary\\openlibrary\\catalog\\utils\\__init__.py": {"loc": 368, "lloc": 224, "sloc": 230, "comments": 6, "multi": 50, "blank": 81, "single_comments": 7}, "openlibrary\\openlibrary\\core\\admin.py": {"loc": 173, "lloc": 84, "sloc": 110, "comments": 6, "multi": 26, "blank": 30, "single_comments": 7}, "openlibrary\\openlibrary\\core\\booknotes.py": {"loc": 219, "lloc": 108, "sloc": 162, "comments": 1, "multi": 33, "blank": 22, "single_comments": 2}, "openlibrary\\openlibrary\\core\\bookshelves.py": {"loc": 631, "lloc": 278, "sloc": 447, "comments": 26, "multi": 97, "blank": 67, "single_comments": 20}, "openlibrary\\openlibrary\\core\\bookshelves_events.py": {"loc": 208, "lloc": 102, "sloc": 161, "comments": 4, "multi": 3, "blank": 40, "single_comments": 4}, "openlibrary\\openlibrary\\core\\cache.py": {"loc": 593, "lloc": 307, "sloc": 319, "comments": 9, "multi": 117, "blank": 143, "single_comments": 14}, "openlibrary\\openlibrary\\core\\civicrm.py": {"loc": 108, "lloc": 55, "sloc": 94, "comments": 2, "multi": 0, "blank": 13, "single_comments": 1}, "openlibrary\\openlibrary\\core\\db.py": {"loc": 187, "lloc": 107, "sloc": 131, "comments": 7, "multi": 21, "blank": 29, "single_comments": 6}, "openlibrary\\openlibrary\\core\\edits.py": {"loc": 335, "lloc": 164, "sloc": 244, "comments": 7, "multi": 30, "blank": 54, "single_comments": 7}, "openlibrary\\openlibrary\\core\\formats.py": {"loc": 34, "lloc": 23, "sloc": 22, "comments": 0, "multi": 2, "blank": 10, "single_comments": 0}, "openlibrary\\openlibrary\\core\\fulltext.py": {"loc": 62, "lloc": 44, "sloc": 54, "comments": 0, "multi": 0, "blank": 8, "single_comments": 0}, "openlibrary\\openlibrary\\core\\helpers.py": {"loc": 332, "lloc": 168, "sloc": 189, "comments": 12, "multi": 50, "blank": 78, "single_comments": 15}, "openlibrary\\openlibrary\\core\\ia.py": {"loc": 395, "lloc": 202, "sloc": 238, "comments": 15, "multi": 67, "blank": 72, "single_comments": 18}, "openlibrary\\openlibrary\\core\\imports.py": {"loc": 430, "lloc": 233, "sloc": 324, "comments": 17, "multi": 26, "blank": 62, "single_comments": 18}, "openlibrary\\openlibrary\\core\\lending.py": {"loc": 1101, "lloc": 614, "sloc": 752, "comments": 83, "multi": 74, "blank": 194, "single_comments": 81}, "openlibrary\\openlibrary\\core\\middleware.py": {"loc": 50, "lloc": 37, "sloc": 37, "comments": 0, "multi": 2, "blank": 10, "single_comments": 1}, "openlibrary\\openlibrary\\core\\models.py": {"loc": 1210, "lloc": 714, "sloc": 799, "comments": 47, "multi": 149, "blank": 210, "single_comments": 52}, "openlibrary\\openlibrary\\core\\observations.py": {"loc": 1111, "lloc": 253, "sloc": 866, "comments": 7, "multi": 132, "blank": 105, "single_comments": 8}, "openlibrary\\openlibrary\\core\\olmarkdown.py": {"loc": 83, "lloc": 36, "sloc": 41, "comments": 4, "multi": 16, "blank": 22, "single_comments": 4}, "openlibrary\\openlibrary\\core\\ratings.py": {"loc": 221, "lloc": 137, "sloc": 183, "comments": 5, "multi": 9, "blank": 25, "single_comments": 4}, "openlibrary\\openlibrary\\core\\schema.py": {"loc": 116, "lloc": 34, "sloc": 88, "comments": 3, "multi": 2, "blank": 22, "single_comments": 4}, "openlibrary\\openlibrary\\core\\sendmail.py": {"loc": 26, "lloc": 14, "sloc": 21, "comments": 0, "multi": 0, "blank": 5, "single_comments": 0}, "openlibrary\\openlibrary\\core\\seq.py": {"loc": 21, "lloc": 8, "sloc": 5, "comments": 0, "multi": 8, "blank": 7, "single_comments": 1}, "openlibrary\\openlibrary\\core\\sponsorships.py": {"loc": 370, "lloc": 157, "sloc": 255, "comments": 19, "multi": 63, "blank": 35, "single_comments": 17}, "openlibrary\\openlibrary\\core\\stats.py": {"loc": 59, "lloc": 37, "sloc": 33, "comments": 3, "multi": 4, "blank": 16, "single_comments": 6}, "openlibrary\\openlibrary\\core\\statsdb.py": {"loc": 67, "lloc": 33, "sloc": 34, "comments": 0, "multi": 19, "blank": 14, "single_comments": 0}, "openlibrary\\openlibrary\\core\\vendors.py": {"loc": 551, "lloc": 201, "sloc": 366, "comments": 15, "multi": 107, "blank": 66, "single_comments": 12}, "openlibrary\\openlibrary\\core\\waitinglist.py": {"loc": 342, "lloc": 200, "sloc": 215, "comments": 21, "multi": 35, "blank": 67, "single_comments": 25}, "openlibrary\\openlibrary\\core\\yearly_reading_goals.py": {"loc": 112, "lloc": 61, "sloc": 83, "comments": 4, "multi": 0, "blank": 25, "single_comments": 4}, "openlibrary\\openlibrary\\core\\__init__.py": {"loc": 4, "lloc": 1, "sloc": 0, "comments": 0, "multi": 3, "blank": 1, "single_comments": 0}, "openlibrary\\openlibrary\\core\\lists\\engine.py": {"loc": 106, "lloc": 78, "sloc": 73, "comments": 0, "multi": 2, "blank": 28, "single_comments": 3}, "openlibrary\\openlibrary\\core\\lists\\model.py": {"loc": 594, "lloc": 380, "sloc": 412, "comments": 11, "multi": 65, "blank": 101, "single_comments": 16}, "openlibrary\\openlibrary\\core\\lists\\__init__.py": {"loc": 0, "lloc": 0, "sloc": 0, "comments": 0, "multi": 0, "blank": 0, "single_comments": 0}, "openlibrary\\openlibrary\\core\\processors\\invalidation.py": {"loc": 179, "lloc": 74, "sloc": 82, "comments": 5, "multi": 46, "blank": 45, "single_comments": 6}, "openlibrary\\openlibrary\\core\\processors\\readableurls.py": {"loc": 202, "lloc": 109, "sloc": 121, "comments": 18, "multi": 16, "blank": 46, "single_comments": 19}, "openlibrary\\openlibrary\\core\\processors\\__init__.py": {"loc": 1, "lloc": 1, "sloc": 1, "comments": 0, "multi": 0, "blank": 0, "single_comments": 0}, "openlibrary\\openlibrary\\coverstore\\archive.py": {"loc": 511, "lloc": 301, "sloc": 365, "comments": 10, "multi": 47, "blank": 84, "single_comments": 15}, "openlibrary\\openlibrary\\coverstore\\code.py": {"loc": 604, "lloc": 397, "sloc": 472, "comments": 16, "multi": 5, "blank": 112, "single_comments": 15}, "openlibrary\\openlibrary\\coverstore\\config.py": {"loc": 16, "lloc": 10, "sloc": 8, "comments": 3, "multi": 0, "blank": 5, "single_comments": 3}, "openlibrary\\openlibrary\\coverstore\\coverlib.py": {"loc": 134, "lloc": 85, "sloc": 97, "comments": 3, "multi": 3, "blank": 28, "single_comments": 6}, "openlibrary\\openlibrary\\coverstore\\db.py": {"loc": 149, "lloc": 78, "sloc": 121, "comments": 0, "multi": 3, "blank": 25, "single_comments": 0}, "openlibrary\\openlibrary\\coverstore\\disk.py": {"loc": 82, "lloc": 47, "sloc": 45, "comments": 0, "multi": 18, "blank": 19, "single_comments": 0}, "openlibrary\\openlibrary\\coverstore\\oldb.py": {"loc": 83, "lloc": 46, "sloc": 58, "comments": 2, "multi": 2, "blank": 21, "single_comments": 2}, "openlibrary\\openlibrary\\coverstore\\schema.py": {"loc": 55, "lloc": 17, "sloc": 45, "comments": 1, "multi": 0, "blank": 8, "single_comments": 2}, "openlibrary\\openlibrary\\coverstore\\server.py": {"loc": 59, "lloc": 39, "sloc": 36, "comments": 1, "multi": 2, "blank": 19, "single_comments": 2}, "openlibrary\\openlibrary\\coverstore\\utils.py": {"loc": 185, "lloc": 119, "sloc": 118, "comments": 2, "multi": 25, "blank": 40, "single_comments": 2}, "openlibrary\\openlibrary\\coverstore\\__init__.py": {"loc": 2, "lloc": 1, "sloc": 0, "comments": 0, "multi": 2, "blank": 0, "single_comments": 0}, "openlibrary\\openlibrary\\coverstore\\tests\\test_archive.py": {"loc": 40, "lloc": 12, "sloc": 27, "comments": 4, "multi": 0, "blank": 9, "single_comments": 4}, "openlibrary\\openlibrary\\coverstore\\tests\\test_code.py": {"loc": 71, "lloc": 45, "sloc": 54, "comments": 0, "multi": 0, "blank": 17, "single_comments": 0}, "openlibrary\\openlibrary\\coverstore\\tests\\test_coverstore.py": {"loc": 155, "lloc": 90, "sloc": 112, "comments": 2, "multi": 0, "blank": 39, "single_comments": 4}, "openlibrary\\openlibrary\\coverstore\\tests\\test_doctests.py": {"loc": 23, "lloc": 14, "sloc": 20, "comments": 0, "multi": 0, "blank": 3, "single_comments": 0}, "openlibrary\\openlibrary\\coverstore\\tests\\test_webapp.py": {"loc": 211, "lloc": 154, "sloc": 158, "comments": 0, "multi": 0, "blank": 51, "single_comments": 2}, "openlibrary\\openlibrary\\coverstore\\tests\\__init__.py": {"loc": 1, "lloc": 1, "sloc": 0, "comments": 0, "multi": 0, "blank": 0, "single_comments": 1}, "openlibrary\\openlibrary\\data\\db.py": {"loc": 228, "lloc": 117, "sloc": 147, "comments": 6, "multi": 28, "blank": 45, "single_comments": 8}, "openlibrary\\openlibrary\\data\\dump.py": {"loc": 361, "lloc": 229, "sloc": 239, "comments": 18, "multi": 27, "blank": 72, "single_comments": 23}, "openlibrary\\openlibrary\\data\\mapreduce.py": {"loc": 123, "lloc": 75, "sloc": 67, "comments": 2, "multi": 27, "blank": 26, "single_comments": 3}, "openlibrary\\openlibrary\\data\\sitemap.py": {"loc": 161, "lloc": 68, "sloc": 109, "comments": 1, "multi": 11, "blank": 40, "single_comments": 1}, "openlibrary\\openlibrary\\data\\__init__.py": {"loc": 15, "lloc": 9, "sloc": 7, "comments": 0, "multi": 3, "blank": 4, "single_comments": 1}, "openlibrary\\openlibrary\\i18n\\test_po_files.py": {"loc": 92, "lloc": 52, "sloc": 53, "comments": 3, "multi": 20, "blank": 16, "single_comments": 3}, "openlibrary\\openlibrary\\i18n\\validators.py": {"loc": 72, "lloc": 23, "sloc": 33, "comments": 0, "multi": 26, "blank": 13, "single_comments": 0}, "openlibrary\\openlibrary\\i18n\\__init__.py": {"loc": 382, "lloc": 244, "sloc": 279, "comments": 7, "multi": 5, "blank": 85, "single_comments": 13}, "openlibrary\\openlibrary\\mocks\\mock_ia.py": {"loc": 31, "lloc": 15, "sloc": 13, "comments": 0, "multi": 9, "blank": 9, "single_comments": 0}, "openlibrary\\openlibrary\\mocks\\mock_infobase.py": {"loc": 400, "lloc": 273, "sloc": 305, "comments": 7, "multi": 8, "blank": 81, "single_comments": 6}, "openlibrary\\openlibrary\\mocks\\mock_memcache.py": {"loc": 52, "lloc": 36, "sloc": 33, "comments": 0, "multi": 2, "blank": 15, "single_comments": 2}, "openlibrary\\openlibrary\\mocks\\mock_ol.py": {"loc": 100, "lloc": 60, "sloc": 63, "comments": 2, "multi": 6, "blank": 29, "single_comments": 2}, "openlibrary\\openlibrary\\mocks\\__init__.py": {"loc": 0, "lloc": 0, "sloc": 0, "comments": 0, "multi": 0, "blank": 0, "single_comments": 0}, "openlibrary\\openlibrary\\mocks\\tests\\test_mock_infobase.py": {"loc": 106, "lloc": 71, "sloc": 83, "comments": 2, "multi": 0, "blank": 21, "single_comments": 2}, "openlibrary\\openlibrary\\mocks\\tests\\test_mock_memcache.py": {"loc": 32, "lloc": 20, "sloc": 20, "comments": 0, "multi": 0, "blank": 12, "single_comments": 0}, "openlibrary\\openlibrary\\mocks\\tests\\__init__.py": {"loc": 0, "lloc": 0, "sloc": 0, "comments": 0, "multi": 0, "blank": 0, "single_comments": 0}, "openlibrary\\openlibrary\\olbase\\events.py": {"loc": 133, "lloc": 79, "sloc": 72, "comments": 2, "multi": 22, "blank": 31, "single_comments": 8}, "openlibrary\\openlibrary\\olbase\\__init__.py": {"loc": 10, "lloc": 6, "sloc": 5, "comments": 0, "multi": 2, "blank": 3, "single_comments": 0}, "openlibrary\\openlibrary\\olbase\\tests\\test_events.py": {"loc": 95, "lloc": 32, "sloc": 85, "comments": 0, "multi": 0, "blank": 10, "single_comments": 0}, "openlibrary\\openlibrary\\olbase\\tests\\test_ol_infobase.py": {"loc": 13, "lloc": 11, "sloc": 11, "comments": 0, "multi": 0, "blank": 2, "single_comments": 0}, "openlibrary\\openlibrary\\olbase\\tests\\__init__.py": {"loc": 0, "lloc": 0, "sloc": 0, "comments": 0, "multi": 0, "blank": 0, "single_comments": 0}, "openlibrary\\openlibrary\\plugins\\ol_infobase.py": {"loc": 610, "lloc": 383, "sloc": 436, "comments": 25, "multi": 8, "blank": 136, "single_comments": 30}, "openlibrary\\openlibrary\\plugins\\__init__.py": {"loc": 1, "lloc": 1, "sloc": 0, "comments": 0, "multi": 0, "blank": 0, "single_comments": 1}, "openlibrary\\openlibrary\\plugins\\admin\\code.py": {"loc": 1011, "lloc": 657, "sloc": 769, "comments": 17, "multi": 15, "blank": 208, "single_comments": 19}, "openlibrary\\openlibrary\\plugins\\admin\\graphs.py": {"loc": 85, "lloc": 39, "sloc": 37, "comments": 1, "multi": 19, "blank": 25, "single_comments": 4}, "openlibrary\\openlibrary\\plugins\\admin\\mem.py": {"loc": 134, "lloc": 97, "sloc": 97, "comments": 1, "multi": 0, "blank": 37, "single_comments": 0}, "openlibrary\\openlibrary\\plugins\\admin\\memory.py": {"loc": 78, "lloc": 47, "sloc": 51, "comments": 0, "multi": 2, "blank": 21, "single_comments": 4}, "openlibrary\\openlibrary\\plugins\\admin\\services.py": {"loc": 72, "lloc": 44, "sloc": 46, "comments": 4, "multi": 10, "blank": 11, "single_comments": 5}, "openlibrary\\openlibrary\\plugins\\admin\\__init__.py": {"loc": 0, "lloc": 0, "sloc": 0, "comments": 0, "multi": 0, "blank": 0, "single_comments": 0}, "openlibrary\\openlibrary\\plugins\\admin\\tests\\conftest.py": {"loc": 11, "lloc": 8, "sloc": 8, "comments": 0, "multi": 0, "blank": 3, "single_comments": 0}, "openlibrary\\openlibrary\\plugins\\admin\\tests\\test_services.py": {"loc": 18, "lloc": 13, "sloc": 11, "comments": 0, "multi": 3, "blank": 3, "single_comments": 1}, "openlibrary\\openlibrary\\plugins\\admin\\tests\\__init__.py": {"loc": 0, "lloc": 0, "sloc": 0, "comments": 0, "multi": 0, "blank": 0, "single_comments": 0}, "openlibrary\\openlibrary\\plugins\\books\\code.py": {"loc": 97, "lloc": 47, "sloc": 45, "comments": 5, "multi": 23, "blank": 23, "single_comments": 6}, "openlibrary\\openlibrary\\plugins\\books\\dynlinks.py": {"loc": 531, "lloc": 284, "sloc": 354, "comments": 16, "multi": 54, "blank": 105, "single_comments": 18}, "openlibrary\\openlibrary\\plugins\\books\\readlinks.py": {"loc": 413, "lloc": 273, "sloc": 321, "comments": 31, "multi": 6, "blank": 57, "single_comments": 29}, "openlibrary\\openlibrary\\plugins\\books\\__init__.py": {"loc": 1, "lloc": 1, "sloc": 0, "comments": 0, "multi": 0, "blank": 0, "single_comments": 1}, "openlibrary\\openlibrary\\plugins\\books\\tests\\test_doctests.py": {"loc": 17, "lloc": 13, "sloc": 13, "comments": 0, "multi": 0, "blank": 4, "single_comments": 0}, "openlibrary\\openlibrary\\plugins\\books\\tests\\test_dynlinks.py": {"loc": 429, "lloc": 147, "sloc": 368, "comments": 1, "multi": 6, "blank": 55, "single_comments": 0}, "openlibrary\\openlibrary\\plugins\\books\\tests\\test_readlinks.py": {"loc": 43, "lloc": 18, "sloc": 38, "comments": 0, "multi": 0, "blank": 5, "single_comments": 0}, "openlibrary\\openlibrary\\plugins\\books\\tests\\__init__.py": {"loc": 0, "lloc": 0, "sloc": 0, "comments": 0, "multi": 0, "blank": 0, "single_comments": 0}, "openlibrary\\openlibrary\\plugins\\importapi\\code.py": {"loc": 745, "lloc": 438, "sloc": 479, "comments": 33, "multi": 111, "blank": 121, "single_comments": 34}, "openlibrary\\openlibrary\\plugins\\importapi\\import_edition_builder.py": {"loc": 153, "lloc": 36, "sloc": 52, "comments": 2, "multi": 83, "blank": 16, "single_comments": 2}, "openlibrary\\openlibrary\\plugins\\importapi\\import_opds.py": {"loc": 68, "lloc": 36, "sloc": 48, "comments": 2, "multi": 3, "blank": 15, "single_comments": 2}, "openlibrary\\openlibrary\\plugins\\importapi\\import_rdf.py": {"loc": 89, "lloc": 53, "sloc": 66, "comments": 4, "multi": 3, "blank": 16, "single_comments": 4}, "openlibrary\\openlibrary\\plugins\\importapi\\import_validator.py": {"loc": 36, "lloc": 28, "sloc": 21, "comments": 0, "multi": 3, "blank": 12, "single_comments": 0}, "openlibrary\\openlibrary\\plugins\\importapi\\metaxml_to_json.py": {"loc": 105, "lloc": 45, "sloc": 51, "comments": 2, "multi": 30, "blank": 22, "single_comments": 2}, "openlibrary\\openlibrary\\plugins\\importapi\\__init__.py": {"loc": 1, "lloc": 1, "sloc": 0, "comments": 0, "multi": 0, "blank": 0, "single_comments": 1}, "openlibrary\\openlibrary\\plugins\\importapi\\tests\\test_code.py": {"loc": 113, "lloc": 35, "sloc": 86, "comments": 3, "multi": 13, "blank": 14, "single_comments": 0}, "openlibrary\\openlibrary\\plugins\\importapi\\tests\\test_code_ils.py": {"loc": 73, "lloc": 31, "sloc": 61, "comments": 0, "multi": 2, "blank": 10, "single_comments": 0}, "openlibrary\\openlibrary\\plugins\\importapi\\tests\\test_import_edition_builder.py": {"loc": 87, "lloc": 9, "sloc": 83, "comments": 1, "multi": 0, "blank": 3, "single_comments": 1}, "openlibrary\\openlibrary\\plugins\\importapi\\tests\\test_import_validator.py": {"loc": 61, "lloc": 36, "sloc": 44, "comments": 0, "multi": 0, "blank": 17, "single_comments": 0}, "openlibrary\\openlibrary\\plugins\\importapi\\tests\\__init__.py": {"loc": 0, "lloc": 0, "sloc": 0, "comments": 0, "multi": 0, "blank": 0, "single_comments": 0}, "openlibrary\\openlibrary\\plugins\\inside\\code.py": {"loc": 46, "lloc": 28, "sloc": 35, "comments": 1, "multi": 0, "blank": 11, "single_comments": 0}, "openlibrary\\openlibrary\\plugins\\inside\\__init__.py": {"loc": 1, "lloc": 1, "sloc": 0, "comments": 0, "multi": 0, "blank": 0, "single_comments": 1}, "openlibrary\\openlibrary\\plugins\\inside\\test\\test_inside.py": {"loc": 0, "lloc": 0, "sloc": 0, "comments": 0, "multi": 0, "blank": 0, "single_comments": 0}, "openlibrary\\openlibrary\\plugins\\openlibrary\\api.py": {"loc": 666, "lloc": 358, "sloc": 494, "comments": 14, "multi": 34, "blank": 127, "single_comments": 11}, "openlibrary\\openlibrary\\plugins\\openlibrary\\authors.py": {"loc": 13, "lloc": 8, "sloc": 8, "comments": 0, "multi": 0, "blank": 5, "single_comments": 0}, "openlibrary\\openlibrary\\plugins\\openlibrary\\borrow_home.py": {"loc": 96, "lloc": 51, "sloc": 59, "comments": 6, "multi": 5, "blank": 26, "single_comments": 6}, "openlibrary\\openlibrary\\plugins\\openlibrary\\bulk_tag.py": {"loc": 75, "lloc": 42, "sloc": 56, "comments": 6, "multi": 0, "blank": 16, "single_comments": 3}, "openlibrary\\openlibrary\\plugins\\openlibrary\\code.py": {"loc": 1181, "lloc": 713, "sloc": 865, "comments": 33, "multi": 27, "blank": 260, "single_comments": 29}, "openlibrary\\openlibrary\\plugins\\openlibrary\\connection.py": {"loc": 620, "lloc": 399, "sloc": 437, "comments": 48, "multi": 20, "blank": 115, "single_comments": 48}, "openlibrary\\openlibrary\\plugins\\openlibrary\\design.py": {"loc": 18, "lloc": 11, "sloc": 11, "comments": 0, "multi": 0, "blank": 7, "single_comments": 0}, "openlibrary\\openlibrary\\plugins\\openlibrary\\dev_instance.py": {"loc": 185, "lloc": 105, "sloc": 115, "comments": 9, "multi": 13, "blank": 47, "single_comments": 10}, "openlibrary\\openlibrary\\plugins\\openlibrary\\events.py": {"loc": 29, "lloc": 17, "sloc": 13, "comments": 2, "multi": 2, "blank": 9, "single_comments": 5}, "openlibrary\\openlibrary\\plugins\\openlibrary\\filters.py": {"loc": 32, "lloc": 18, "sloc": 14, "comments": 2, "multi": 3, "blank": 10, "single_comments": 5}, "openlibrary\\openlibrary\\plugins\\openlibrary\\home.py": {"loc": 302, "lloc": 145, "sloc": 223, "comments": 18, "multi": 2, "blank": 58, "single_comments": 19}, "openlibrary\\openlibrary\\plugins\\openlibrary\\infobase_hook.py": {"loc": 28, "lloc": 15, "sloc": 12, "comments": 2, "multi": 6, "blank": 8, "single_comments": 2}, "openlibrary\\openlibrary\\plugins\\openlibrary\\lists.py": {"loc": 943, "lloc": 580, "sloc": 725, "comments": 23, "multi": 15, "blank": 187, "single_comments": 16}, "openlibrary\\openlibrary\\plugins\\openlibrary\\opds.py": {"loc": 315, "lloc": 161, "sloc": 227, "comments": 30, "multi": 12, "blank": 47, "single_comments": 29}, "openlibrary\\openlibrary\\plugins\\openlibrary\\processors.py": {"loc": 91, "lloc": 52, "sloc": 65, "comments": 4, "multi": 5, "blank": 17, "single_comments": 4}, "openlibrary\\openlibrary\\plugins\\openlibrary\\schema.py": {"loc": 5, "lloc": 4, "sloc": 3, "comments": 0, "multi": 0, "blank": 1, "single_comments": 1}, "openlibrary\\openlibrary\\plugins\\openlibrary\\sentry.py": {"loc": 15, "lloc": 13, "sloc": 11, "comments": 0, "multi": 0, "blank": 4, "single_comments": 0}, "openlibrary\\openlibrary\\plugins\\openlibrary\\stats.py": {"loc": 323, "lloc": 195, "sloc": 209, "comments": 20, "multi": 30, "blank": 68, "single_comments": 16}, "openlibrary\\openlibrary\\plugins\\openlibrary\\status.py": {"loc": 119, "lloc": 88, "sloc": 93, "comments": 1, "multi": 0, "blank": 23, "single_comments": 3}, "openlibrary\\openlibrary\\plugins\\openlibrary\\support.py": {"loc": 107, "lloc": 61, "sloc": 84, "comments": 0, "multi": 0, "blank": 23, "single_comments": 0}, "openlibrary\\openlibrary\\plugins\\openlibrary\\swagger.py": {"loc": 13, "lloc": 8, "sloc": 8, "comments": 0, "multi": 0, "blank": 5, "single_comments": 0}, "openlibrary\\openlibrary\\plugins\\openlibrary\\utils.py": {"loc": 1, "lloc": 1, "sloc": 1, "comments": 0, "multi": 0, "blank": 0, "single_comments": 0}, "openlibrary\\openlibrary\\plugins\\openlibrary\\__init__.py": {"loc": 3, "lloc": 1, "sloc": 0, "comments": 0, "multi": 3, "blank": 0, "single_comments": 0}, "openlibrary\\openlibrary\\plugins\\openlibrary\\tests\\conftest.py": {"loc": 14, "lloc": 10, "sloc": 9, "comments": 0, "multi": 0, "blank": 5, "single_comments": 0}, "openlibrary\\openlibrary\\plugins\\openlibrary\\tests\\test_home.py": {"loc": 180, "lloc": 82, "sloc": 152, "comments": 3, "multi": 0, "blank": 25, "single_comments": 3}, "openlibrary\\openlibrary\\plugins\\openlibrary\\tests\\test_listapi.py": {"loc": 135, "lloc": 82, "sloc": 97, "comments": 6, "multi": 0, "blank": 31, "single_comments": 7}, "openlibrary\\openlibrary\\plugins\\openlibrary\\tests\\test_lists.py": {"loc": 108, "lloc": 45, "sloc": 98, "comments": 0, "multi": 0, "blank": 10, "single_comments": 0}, "openlibrary\\openlibrary\\plugins\\openlibrary\\tests\\test_ratingsapi.py": {"loc": 65, "lloc": 51, "sloc": 46, "comments": 1, "multi": 0, "blank": 17, "single_comments": 2}, "openlibrary\\openlibrary\\plugins\\openlibrary\\tests\\test_stats.py": {"loc": 78, "lloc": 68, "sloc": 51, "comments": 4, "multi": 3, "blank": 15, "single_comments": 9}, "openlibrary\\openlibrary\\plugins\\openlibrary\\tests\\__init__.py": {"loc": 0, "lloc": 0, "sloc": 0, "comments": 0, "multi": 0, "blank": 0, "single_comments": 0}, "openlibrary\\openlibrary\\plugins\\recaptcha\\code.py": {"loc": 14, "lloc": 0, "sloc": 0, "comments": 14, "multi": 0, "blank": 0, "single_comments": 14}, "openlibrary\\openlibrary\\plugins\\recaptcha\\recaptcha.py": {"loc": 37, "lloc": 24, "sloc": 28, "comments": 0, "multi": 0, "blank": 8, "single_comments": 1}, "openlibrary\\openlibrary\\plugins\\recaptcha\\__init__.py": {"loc": 0, "lloc": 0, "sloc": 0, "comments": 0, "multi": 0, "blank": 0, "single_comments": 0}, "openlibrary\\openlibrary\\plugins\\upstream\\account.py": {"loc": 1263, "lloc": 720, "sloc": 924, "comments": 43, "multi": 78, "blank": 222, "single_comments": 39}, "openlibrary\\openlibrary\\plugins\\upstream\\adapter.py": {"loc": 297, "lloc": 189, "sloc": 221, "comments": 5, "multi": 15, "blank": 60, "single_comments": 1}, "openlibrary\\openlibrary\\plugins\\upstream\\addbook.py": {"loc": 1075, "lloc": 589, "sloc": 712, "comments": 43, "multi": 121, "blank": 201, "single_comments": 41}, "openlibrary\\openlibrary\\plugins\\upstream\\addtag.py": {"loc": 163, "lloc": 97, "sloc": 106, "comments": 5, "multi": 15, "blank": 36, "single_comments": 6}, "openlibrary\\openlibrary\\plugins\\upstream\\borrow.py": {"loc": 944, "lloc": 520, "sloc": 599, "comments": 83, "multi": 47, "blank": 207, "single_comments": 91}, "openlibrary\\openlibrary\\plugins\\upstream\\checkins.py": {"loc": 282, "lloc": 168, "sloc": 183, "comments": 6, "multi": 23, "blank": 69, "single_comments": 7}, "openlibrary\\openlibrary\\plugins\\upstream\\code.py": {"loc": 424, "lloc": 272, "sloc": 309, "comments": 10, "multi": 3, "blank": 95, "single_comments": 17}, "openlibrary\\openlibrary\\plugins\\upstream\\covers.py": {"loc": 170, "lloc": 118, "sloc": 122, "comments": 2, "multi": 2, "blank": 43, "single_comments": 3}, "openlibrary\\openlibrary\\plugins\\upstream\\data.py": {"loc": 93, "lloc": 52, "sloc": 61, "comments": 2, "multi": 2, "blank": 27, "single_comments": 3}, "openlibrary\\openlibrary\\plugins\\upstream\\edits.py": {"loc": 208, "lloc": 105, "sloc": 171, "comments": 8, "multi": 2, "blank": 27, "single_comments": 8}, "openlibrary\\openlibrary\\plugins\\upstream\\forms.py": {"loc": 157, "lloc": 59, "sloc": 128, "comments": 3, "multi": 0, "blank": 26, "single_comments": 3}, "openlibrary\\openlibrary\\plugins\\upstream\\jsdef.py": {"loc": 270, "lloc": 132, "sloc": 124, "comments": 5, "multi": 81, "blank": 63, "single_comments": 2}, "openlibrary\\openlibrary\\plugins\\upstream\\merge_authors.py": {"loc": 386, "lloc": 232, "sloc": 254, "comments": 19, "multi": 36, "blank": 76, "single_comments": 20}, "openlibrary\\openlibrary\\plugins\\upstream\\models.py": {"loc": 1009, "lloc": 614, "sloc": 711, "comments": 50, "multi": 48, "blank": 189, "single_comments": 61}, "openlibrary\\openlibrary\\plugins\\upstream\\mybooks.py": {"loc": 615, "lloc": 294, "sloc": 493, "comments": 20, "multi": 15, "blank": 86, "single_comments": 21}, "openlibrary\\openlibrary\\plugins\\upstream\\recentchanges.py": {"loc": 197, "lloc": 134, "sloc": 142, "comments": 5, "multi": 3, "blank": 48, "single_comments": 4}, "openlibrary\\openlibrary\\plugins\\upstream\\spamcheck.py": {"loc": 64, "lloc": 42, "sloc": 42, "comments": 4, "multi": 0, "blank": 18, "single_comments": 4}, "openlibrary\\openlibrary\\plugins\\upstream\\utils.py": {"loc": 1712, "lloc": 786, "sloc": 1170, "comments": 61, "multi": 163, "blank": 318, "single_comments": 61}, "openlibrary\\openlibrary\\plugins\\upstream\\__init__.py": {"loc": 0, "lloc": 0, "sloc": 0, "comments": 0, "multi": 0, "blank": 0, "single_comments": 0}, "openlibrary\\openlibrary\\plugins\\upstream\\tests\\test_account.py": {"loc": 335, "lloc": 134, "sloc": 284, "comments": 4, "multi": 0, "blank": 47, "single_comments": 4}, "openlibrary\\openlibrary\\plugins\\upstream\\tests\\test_addbook.py": {"loc": 458, "lloc": 166, "sloc": 381, "comments": 3, "multi": 0, "blank": 74, "single_comments": 3}, "openlibrary\\openlibrary\\plugins\\upstream\\tests\\test_checkins.py": {"loc": 79, "lloc": 42, "sloc": 64, "comments": 5, "multi": 0, "blank": 10, "single_comments": 5}, "openlibrary\\openlibrary\\plugins\\upstream\\tests\\test_forms.py": {"loc": 18, "lloc": 13, "sloc": 15, "comments": 0, "multi": 0, "blank": 3, "single_comments": 0}, "openlibrary\\openlibrary\\plugins\\upstream\\tests\\test_merge_authors.py": {"loc": 314, "lloc": 164, "sloc": 240, "comments": 9, "multi": 3, "blank": 62, "single_comments": 9}, "openlibrary\\openlibrary\\plugins\\upstream\\tests\\test_models.py": {"loc": 95, "lloc": 67, "sloc": 76, "comments": 8, "multi": 3, "blank": 11, "single_comments": 5}, "openlibrary\\openlibrary\\plugins\\upstream\\tests\\test_related_carousels.py": {"loc": 66, "lloc": 6, "sloc": 64, "comments": 0, "multi": 0, "blank": 2, "single_comments": 0}, "openlibrary\\openlibrary\\plugins\\upstream\\tests\\test_utils.py": {"loc": 303, "lloc": 159, "sloc": 229, "comments": 18, "multi": 0, "blank": 59, "single_comments": 15}, "openlibrary\\openlibrary\\plugins\\upstream\\tests\\__init__.py": {"loc": 0, "lloc": 0, "sloc": 0, "comments": 0, "multi": 0, "blank": 0, "single_comments": 0}, "openlibrary\\openlibrary\\plugins\\worksearch\\autocomplete.py": {"loc": 158, "lloc": 108, "sloc": 114, "comments": 7, "multi": 0, "blank": 35, "single_comments": 9}, "openlibrary\\openlibrary\\plugins\\worksearch\\code.py": {"loc": 855, "lloc": 416, "sloc": 667, "comments": 29, "multi": 31, "blank": 131, "single_comments": 26}, "openlibrary\\openlibrary\\plugins\\worksearch\\languages.py": {"loc": 132, "lloc": 76, "sloc": 92, "comments": 2, "multi": 2, "blank": 37, "single_comments": 1}, "openlibrary\\openlibrary\\plugins\\worksearch\\publishers.py": {"loc": 113, "lloc": 62, "sloc": 82, "comments": 2, "multi": 2, "blank": 28, "single_comments": 1}, "openlibrary\\openlibrary\\plugins\\worksearch\\search.py": {"loc": 14, "lloc": 11, "sloc": 9, "comments": 0, "multi": 2, "blank": 3, "single_comments": 0}, "openlibrary\\openlibrary\\plugins\\worksearch\\subjects.py": {"loc": 469, "lloc": 172, "sloc": 333, "comments": 10, "multi": 64, "blank": 61, "single_comments": 11}, "openlibrary\\openlibrary\\plugins\\worksearch\\__init__.py": {"loc": 1, "lloc": 1, "sloc": 0, "comments": 0, "multi": 0, "blank": 0, "single_comments": 1}, "openlibrary\\openlibrary\\plugins\\worksearch\\schemes\\authors.py": {"loc": 57, "lloc": 19, "sloc": 52, "comments": 1, "multi": 0, "blank": 5, "single_comments": 0}, "openlibrary\\openlibrary\\plugins\\worksearch\\schemes\\editions.py": {"loc": 66, "lloc": 18, "sloc": 58, "comments": 9, "multi": 0, "blank": 5, "single_comments": 3}, "openlibrary\\openlibrary\\plugins\\worksearch\\schemes\\subjects.py": {"loc": 47, "lloc": 19, "sloc": 42, "comments": 1, "multi": 0, "blank": 5, "single_comments": 0}, "openlibrary\\openlibrary\\plugins\\worksearch\\schemes\\works.py": {"loc": 610, "lloc": 229, "sloc": 521, "comments": 76, "multi": 13, "blank": 42, "single_comments": 34}, "openlibrary\\openlibrary\\plugins\\worksearch\\schemes\\__init__.py": {"loc": 112, "lloc": 49, "sloc": 69, "comments": 15, "multi": 17, "blank": 15, "single_comments": 11}, "openlibrary\\openlibrary\\plugins\\worksearch\\schemes\\tests\\test_works.py": {"loc": 140, "lloc": 22, "sloc": 130, "comments": 3, "multi": 0, "blank": 9, "single_comments": 1}, "openlibrary\\openlibrary\\plugins\\worksearch\\tests\\test_autocomplete.py": {"loc": 109, "lloc": 42, "sloc": 94, "comments": 8, "multi": 0, "blank": 7, "single_comments": 8}, "openlibrary\\openlibrary\\plugins\\worksearch\\tests\\test_worksearch.py": {"loc": 64, "lloc": 10, "sloc": 60, "comments": 0, "multi": 0, "blank": 4, "single_comments": 0}, "openlibrary\\openlibrary\\records\\driver.py": {"loc": 137, "lloc": 53, "sloc": 51, "comments": 12, "multi": 45, "blank": 31, "single_comments": 10}, "openlibrary\\openlibrary\\records\\functions.py": {"loc": 423, "lloc": 227, "sloc": 216, "comments": 28, "multi": 96, "blank": 86, "single_comments": 25}, "openlibrary\\openlibrary\\records\\matchers.py": {"loc": 90, "lloc": 47, "sloc": 39, "comments": 4, "multi": 21, "blank": 24, "single_comments": 6}, "openlibrary\\openlibrary\\records\\__init__.py": {"loc": 2, "lloc": 2, "sloc": 2, "comments": 0, "multi": 0, "blank": 0, "single_comments": 0}, "openlibrary\\openlibrary\\records\\tests\\test_functions.py": {"loc": 473, "lloc": 217, "sloc": 372, "comments": 20, "multi": 6, "blank": 61, "single_comments": 34}, "openlibrary\\openlibrary\\records\\tests\\__init__.py": {"loc": 0, "lloc": 0, "sloc": 0, "comments": 0, "multi": 0, "blank": 0, "single_comments": 0}, "openlibrary\\openlibrary\\solr\\data_provider.py": {"loc": 546, "lloc": 328, "sloc": 350, "comments": 22, "multi": 84, "blank": 88, "single_comments": 24}, "openlibrary\\openlibrary\\solr\\query_utils.py": {"loc": 281, "lloc": 121, "sloc": 135, "comments": 21, "multi": 88, "blank": 37, "single_comments": 21}, "openlibrary\\openlibrary\\solr\\solr_types.py": {"loc": 94, "lloc": 174, "sloc": 88, "comments": 3, "multi": 0, "blank": 3, "single_comments": 3}, "openlibrary\\openlibrary\\solr\\types_generator.py": {"loc": 97, "lloc": 51, "sloc": 78, "comments": 2, "multi": 0, "blank": 16, "single_comments": 3}, "openlibrary\\openlibrary\\solr\\update.py": {"loc": 202, "lloc": 101, "sloc": 144, "comments": 5, "multi": 20, "blank": 35, "single_comments": 3}, "openlibrary\\openlibrary\\solr\\utils.py": {"loc": 206, "lloc": 123, "sloc": 141, "comments": 6, "multi": 16, "blank": 44, "single_comments": 5}, "openlibrary\\openlibrary\\solr\\__init__.py": {"loc": 0, "lloc": 0, "sloc": 0, "comments": 0, "multi": 0, "blank": 0, "single_comments": 0}, "openlibrary\\openlibrary\\solr\\updater\\abstract.py": {"loc": 55, "lloc": 43, "sloc": 38, "comments": 4, "multi": 3, "blank": 10, "single_comments": 4}, "openlibrary\\openlibrary\\solr\\updater\\author.py": {"loc": 92, "lloc": 62, "sloc": 73, "comments": 1, "multi": 0, "blank": 18, "single_comments": 1}, "openlibrary\\openlibrary\\solr\\updater\\edition.py": {"loc": 322, "lloc": 183, "sloc": 246, "comments": 14, "multi": 21, "blank": 47, "single_comments": 8}, "openlibrary\\openlibrary\\solr\\updater\\list.py": {"loc": 115, "lloc": 76, "sloc": 96, "comments": 1, "multi": 0, "blank": 19, "single_comments": 0}, "openlibrary\\openlibrary\\solr\\updater\\work.py": {"loc": 693, "lloc": 387, "sloc": 521, "comments": 45, "multi": 35, "blank": 104, "single_comments": 33}, "openlibrary\\openlibrary\\solr\\updater\\__init__.py": {"loc": 0, "lloc": 0, "sloc": 0, "comments": 0, "multi": 0, "blank": 0, "single_comments": 0}, "openlibrary\\openlibrary\\tests\\accounts\\test_models.py": {"loc": 99, "lloc": 56, "sloc": 80, "comments": 0, "multi": 0, "blank": 19, "single_comments": 0}, "openlibrary\\openlibrary\\tests\\accounts\\__init__.py": {"loc": 0, "lloc": 0, "sloc": 0, "comments": 0, "multi": 0, "blank": 0, "single_comments": 0}, "openlibrary\\openlibrary\\tests\\catalog\\test_get_ia.py": {"loc": 127, "lloc": 51, "sloc": 101, "comments": 6, "multi": 5, "blank": 19, "single_comments": 2}, "openlibrary\\openlibrary\\tests\\catalog\\test_utils.py": {"loc": 348, "lloc": 108, "sloc": 302, "comments": 5, "multi": 4, "blank": 37, "single_comments": 5}, "openlibrary\\openlibrary\\tests\\core\\conftest.py": {"loc": 67, "lloc": 51, "sloc": 43, "comments": 2, "multi": 7, "blank": 14, "single_comments": 3}, "openlibrary\\openlibrary\\tests\\core\\test_cache.py": {"loc": 171, "lloc": 131, "sloc": 124, "comments": 2, "multi": 0, "blank": 44, "single_comments": 3}, "openlibrary\\openlibrary\\tests\\core\\test_connections.py": {"loc": 126, "lloc": 61, "sloc": 104, "comments": 1, "multi": 0, "blank": 21, "single_comments": 1}, "openlibrary\\openlibrary\\tests\\core\\test_db.py": {"loc": 624, "lloc": 245, "sloc": 567, "comments": 0, "multi": 0, "blank": 57, "single_comments": 0}, "openlibrary\\openlibrary\\tests\\core\\test_fulltext.py": {"loc": 34, "lloc": 32, "sloc": 29, "comments": 0, "multi": 0, "blank": 5, "single_comments": 0}, "openlibrary\\openlibrary\\tests\\core\\test_helpers.py": {"loc": 134, "lloc": 73, "sloc": 85, "comments": 9, "multi": 0, "blank": 40, "single_comments": 9}, "openlibrary\\openlibrary\\tests\\core\\test_i18n.py": {"loc": 86, "lloc": 52, "sloc": 64, "comments": 1, "multi": 0, "blank": 21, "single_comments": 1}, "openlibrary\\openlibrary\\tests\\core\\test_ia.py": {"loc": 25, "lloc": 12, "sloc": 20, "comments": 0, "multi": 0, "blank": 5, "single_comments": 0}, "openlibrary\\openlibrary\\tests\\core\\test_imports.py": {"loc": 185, "lloc": 77, "sloc": 153, "comments": 0, "multi": 0, "blank": 28, "single_comments": 4}, "openlibrary\\openlibrary\\tests\\core\\test_lending.py": {"loc": 86, "lloc": 55, "sloc": 69, "comments": 2, "multi": 0, "blank": 15, "single_comments": 2}, "openlibrary\\openlibrary\\tests\\core\\test_lists_engine.py": {"loc": 18, "lloc": 9, "sloc": 15, "comments": 0, "multi": 0, "blank": 3, "single_comments": 0}, "openlibrary\\openlibrary\\tests\\core\\test_lists_model.py": {"loc": 21, "lloc": 17, "sloc": 16, "comments": 0, "multi": 0, "blank": 5, "single_comments": 0}, "openlibrary\\openlibrary\\tests\\core\\test_models.py": {"loc": 119, "lloc": 91, "sloc": 88, "comments": 2, "multi": 0, "blank": 29, "single_comments": 2}, "openlibrary\\openlibrary\\tests\\core\\test_observations.py": {"loc": 22, "lloc": 11, "sloc": 14, "comments": 3, "multi": 0, "blank": 5, "single_comments": 3}, "openlibrary\\openlibrary\\tests\\core\\test_olmarkdown.py": {"loc": 24, "lloc": 11, "sloc": 17, "comments": 2, "multi": 0, "blank": 5, "single_comments": 2}, "openlibrary\\openlibrary\\tests\\core\\test_processors.py": {"loc": 128, "lloc": 73, "sloc": 84, "comments": 6, "multi": 0, "blank": 38, "single_comments": 6}, "openlibrary\\openlibrary\\tests\\core\\test_processors_invalidation.py": {"loc": 194, "lloc": 110, "sloc": 121, "comments": 20, "multi": 0, "blank": 50, "single_comments": 23}, "openlibrary\\openlibrary\\tests\\core\\test_ratings.py": {"loc": 3, "lloc": 3, "sloc": 3, "comments": 0, "multi": 0, "blank": 0, "single_comments": 0}, "openlibrary\\openlibrary\\tests\\core\\test_sponsors.py": {"loc": 75, "lloc": 51, "sloc": 59, "comments": 2, "multi": 0, "blank": 14, "single_comments": 2}, "openlibrary\\openlibrary\\tests\\core\\test_unmarshal.py": {"loc": 73, "lloc": 22, "sloc": 56, "comments": 1, "multi": 4, "blank": 13, "single_comments": 0}, "openlibrary\\openlibrary\\tests\\core\\test_vendors.py": {"loc": 258, "lloc": 69, "sloc": 226, "comments": 9, "multi": 4, "blank": 21, "single_comments": 7}, "openlibrary\\openlibrary\\tests\\core\\test_waitinglist.py": {"loc": 44, "lloc": 31, "sloc": 35, "comments": 3, "multi": 0, "blank": 6, "single_comments": 3}, "openlibrary\\openlibrary\\tests\\core\\__init__.py": {"loc": 0, "lloc": 0, "sloc": 0, "comments": 0, "multi": 0, "blank": 0, "single_comments": 0}, "openlibrary\\openlibrary\\tests\\core\\lists\\test_model.py": {"loc": 29, "lloc": 23, "sloc": 22, "comments": 0, "multi": 0, "blank": 7, "single_comments": 0}, "openlibrary\\openlibrary\\tests\\data\\test_dump.py": {"loc": 61, "lloc": 25, "sloc": 50, "comments": 0, "multi": 0, "blank": 11, "single_comments": 0}, "openlibrary\\openlibrary\\tests\\solr\\test_data_provider.py": {"loc": 55, "lloc": 28, "sloc": 50, "comments": 0, "multi": 0, "blank": 5, "single_comments": 0}, "openlibrary\\openlibrary\\tests\\solr\\test_query_utils.py": {"loc": 101, "lloc": 49, "sloc": 84, "comments": 1, "multi": 0, "blank": 16, "single_comments": 1}, "openlibrary\\openlibrary\\tests\\solr\\test_types_generator.py": {"loc": 16, "lloc": 6, "sloc": 11, "comments": 0, "multi": 0, "blank": 5, "single_comments": 0}, "openlibrary\\openlibrary\\tests\\solr\\test_update.py": {"loc": 142, "lloc": 84, "sloc": 96, "comments": 0, "multi": 19, "blank": 26, "single_comments": 1}, "openlibrary\\openlibrary\\tests\\solr\\test_utils.py": {"loc": 148, "lloc": 47, "sloc": 123, "comments": 0, "multi": 0, "blank": 25, "single_comments": 0}, "openlibrary\\openlibrary\\tests\\solr\\__init__.py": {"loc": 0, "lloc": 0, "sloc": 0, "comments": 0, "multi": 0, "blank": 0, "single_comments": 0}, "openlibrary\\openlibrary\\tests\\solr\\updater\\test_author.py": {"loc": 47, "lloc": 26, "sloc": 39, "comments": 0, "multi": 0, "blank": 8, "single_comments": 0}, "openlibrary\\openlibrary\\tests\\solr\\updater\\test_edition.py": {"loc": 30, "lloc": 18, "sloc": 24, "comments": 0, "multi": 0, "blank": 6, "single_comments": 0}, "openlibrary\\openlibrary\\tests\\solr\\updater\\test_work.py": {"loc": 580, "lloc": 248, "sloc": 515, "comments": 3, "multi": 4, "blank": 59, "single_comments": 2}, "openlibrary\\openlibrary\\tests\\solr\\updater\\__init__.py": {"loc": 0, "lloc": 0, "sloc": 0, "comments": 0, "multi": 0, "blank": 0, "single_comments": 0}, "openlibrary\\openlibrary\\utils\\bulkimport.py": {"loc": 489, "lloc": 226, "sloc": 330, "comments": 17, "multi": 63, "blank": 75, "single_comments": 21}, "openlibrary\\openlibrary\\utils\\compress.py": {"loc": 89, "lloc": 40, "sloc": 63, "comments": 8, "multi": 3, "blank": 15, "single_comments": 8}, "openlibrary\\openlibrary\\utils\\dateutil.py": {"loc": 128, "lloc": 69, "sloc": 60, "comments": 2, "multi": 31, "blank": 34, "single_comments": 3}, "openlibrary\\openlibrary\\utils\\ddc.py": {"loc": 172, "lloc": 78, "sloc": 95, "comments": 25, "multi": 19, "blank": 33, "single_comments": 25}, "openlibrary\\openlibrary\\utils\\decorators.py": {"loc": 30, "lloc": 20, "sloc": 19, "comments": 1, "multi": 0, "blank": 9, "single_comments": 2}, "openlibrary\\openlibrary\\utils\\form.py": {"loc": 210, "lloc": 130, "sloc": 124, "comments": 1, "multi": 20, "blank": 63, "single_comments": 3}, "openlibrary\\openlibrary\\utils\\ia.py": {"loc": 25, "lloc": 19, "sloc": 19, "comments": 0, "multi": 0, "blank": 6, "single_comments": 0}, "openlibrary\\openlibrary\\utils\\isbn.py": {"loc": 120, "lloc": 71, "sloc": 73, "comments": 3, "multi": 21, "blank": 22, "single_comments": 4}, "openlibrary\\openlibrary\\utils\\lcc.py": {"loc": 218, "lloc": 59, "sloc": 69, "comments": 10, "multi": 99, "blank": 41, "single_comments": 9}, "openlibrary\\openlibrary\\utils\\lccn.py": {"loc": 23, "lloc": 15, "sloc": 17, "comments": 2, "multi": 0, "blank": 4, "single_comments": 2}, "openlibrary\\openlibrary\\utils\\olcompress.py": {"loc": 20, "lloc": 10, "sloc": 8, "comments": 5, "multi": 3, "blank": 7, "single_comments": 2}, "openlibrary\\openlibrary\\utils\\olmemcache.py": {"loc": 48, "lloc": 36, "sloc": 32, "comments": 0, "multi": 3, "blank": 12, "single_comments": 1}, "openlibrary\\openlibrary\\utils\\open_syllabus_project.py": {"loc": 116, "lloc": 52, "sloc": 57, "comments": 12, "multi": 20, "blank": 27, "single_comments": 12}, "openlibrary\\openlibrary\\utils\\processors.py": {"loc": 55, "lloc": 35, "sloc": 33, "comments": 0, "multi": 11, "blank": 10, "single_comments": 1}, "openlibrary\\openlibrary\\utils\\retry.py": {"loc": 34, "lloc": 27, "sloc": 25, "comments": 0, "multi": 0, "blank": 9, "single_comments": 0}, "openlibrary\\openlibrary\\utils\\schema.py": {"loc": 404, "lloc": 176, "sloc": 237, "comments": 3, "multi": 77, "blank": 88, "single_comments": 2}, "openlibrary\\openlibrary\\utils\\sentry.py": {"loc": 174, "lloc": 110, "sloc": 125, "comments": 2, "multi": 11, "blank": 36, "single_comments": 2}, "openlibrary\\openlibrary\\utils\\solr.py": {"loc": 200, "lloc": 112, "sloc": 143, "comments": 9, "multi": 9, "blank": 39, "single_comments": 9}, "openlibrary\\openlibrary\\utils\\__init__.py": {"loc": 229, "lloc": 112, "sloc": 110, "comments": 2, "multi": 78, "blank": 38, "single_comments": 3}, "openlibrary\\openlibrary\\utils\\tests\\test_dateutil.py": {"loc": 45, "lloc": 23, "sloc": 32, "comments": 0, "multi": 0, "blank": 13, "single_comments": 0}, "openlibrary\\openlibrary\\utils\\tests\\test_ddc.py": {"loc": 159, "lloc": 22, "sloc": 140, "comments": 2, "multi": 0, "blank": 18, "single_comments": 1}, "openlibrary\\openlibrary\\utils\\tests\\test_isbn.py": {"loc": 82, "lloc": 37, "sloc": 55, "comments": 7, "multi": 0, "blank": 20, "single_comments": 7}, "openlibrary\\openlibrary\\utils\\tests\\test_lcc.py": {"loc": 153, "lloc": 32, "sloc": 122, "comments": 4, "multi": 0, "blank": 28, "single_comments": 3}, "openlibrary\\openlibrary\\utils\\tests\\test_lccn.py": {"loc": 33, "lloc": 10, "sloc": 24, "comments": 1, "multi": 0, "blank": 8, "single_comments": 1}, "openlibrary\\openlibrary\\utils\\tests\\test_processors.py": {"loc": 36, "lloc": 26, "sloc": 22, "comments": 2, "multi": 0, "blank": 11, "single_comments": 3}, "openlibrary\\openlibrary\\utils\\tests\\test_retry.py": {"loc": 40, "lloc": 35, "sloc": 34, "comments": 0, "multi": 0, "blank": 6, "single_comments": 0}, "openlibrary\\openlibrary\\utils\\tests\\test_solr.py": {"loc": 17, "lloc": 10, "sloc": 13, "comments": 0, "multi": 0, "blank": 4, "single_comments": 0}, "openlibrary\\openlibrary\\utils\\tests\\test_utils.py": {"loc": 17, "lloc": 10, "sloc": 13, "comments": 0, "multi": 0, "blank": 4, "single_comments": 0}, "openlibrary\\openlibrary\\utils\\tests\\__init__.py": {"loc": 0, "lloc": 0, "sloc": 0, "comments": 0, "multi": 0, "blank": 0, "single_comments": 0}, "openlibrary\\openlibrary\\views\\loanstats.py": {"loc": 231, "lloc": 104, "sloc": 179, "comments": 9, "multi": 0, "blank": 45, "single_comments": 7}, "openlibrary\\openlibrary\\views\\showmarc.py": {"loc": 146, "lloc": 97, "sloc": 108, "comments": 2, "multi": 3, "blank": 35, "single_comments": 0}, "openlibrary\\openlibrary\\views\\__init__.py": {"loc": 0, "lloc": 0, "sloc": 0, "comments": 0, "multi": 0, "blank": 0, "single_comments": 0}, "openlibrary\\scripts\\affiliate_server.py": {"loc": 530, "lloc": 259, "sloc": 314, "comments": 33, "multi": 79, "blank": 113, "single_comments": 24}, "openlibrary\\scripts\\copydocs.py": {"loc": 389, "lloc": 213, "sloc": 254, "comments": 18, "multi": 42, "blank": 75, "single_comments": 18}, "openlibrary\\scripts\\coverstore-server": {"loc": 88, "lloc": 41, "sloc": 37, "comments": 4, "multi": 15, "blank": 32, "single_comments": 4}, "openlibrary\\scripts\\cron_watcher.py": {"loc": 49, "lloc": 22, "sloc": 19, "comments": 4, "multi": 16, "blank": 10, "single_comments": 4}, "openlibrary\\scripts\\delete_import_items.py": {"loc": 160, "lloc": 93, "sloc": 106, "comments": 9, "multi": 13, "blank": 33, "single_comments": 8}, "openlibrary\\scripts\\expire_accounts.py": {"loc": 26, "lloc": 18, "sloc": 18, "comments": 0, "multi": 0, "blank": 8, "single_comments": 0}, "openlibrary\\scripts\\fake_loan_server.py": {"loc": 18, "lloc": 10, "sloc": 9, "comments": 1, "multi": 3, "blank": 5, "single_comments": 1}, "openlibrary\\scripts\\generate-api-docs.py": {"loc": 130, "lloc": 65, "sloc": 91, "comments": 2, "multi": 0, "blank": 37, "single_comments": 2}, "openlibrary\\scripts\\get_web_error.py": {"loc": 50, "lloc": 21, "sloc": 24, "comments": 1, "multi": 14, "blank": 11, "single_comments": 1}, "openlibrary\\scripts\\i18n-messages": {"loc": 70, "lloc": 51, "sloc": 56, "comments": 3, "multi": 3, "blank": 10, "single_comments": 1}, "openlibrary\\scripts\\import_open_textbook_library.py": {"loc": 150, "lloc": 84, "sloc": 99, "comments": 4, "multi": 9, "blank": 36, "single_comments": 6}, "openlibrary\\scripts\\import_pressbooks.py": {"loc": 149, "lloc": 78, "sloc": 116, "comments": 7, "multi": 4, "blank": 24, "single_comments": 5}, "openlibrary\\scripts\\import_standard_ebooks.py": {"loc": 185, "lloc": 89, "sloc": 92, "comments": 10, "multi": 35, "blank": 45, "single_comments": 13}, "openlibrary\\scripts\\infobase-server": {"loc": 110, "lloc": 60, "sloc": 57, "comments": 10, "multi": 7, "blank": 35, "single_comments": 11}, "openlibrary\\scripts\\lc_marc_update.py": {"loc": 175, "lloc": 143, "sloc": 143, "comments": 4, "multi": 0, "blank": 29, "single_comments": 3}, "openlibrary\\scripts\\mail_bad_author_query.py": {"loc": 59, "lloc": 37, "sloc": 48, "comments": 3, "multi": 0, "blank": 8, "single_comments": 3}, "openlibrary\\scripts\\manage-imports.py": {"loc": 254, "lloc": 180, "sloc": 191, "comments": 5, "multi": 14, "blank": 43, "single_comments": 6}, "openlibrary\\scripts\\migrate_db.py": {"loc": 141, "lloc": 82, "sloc": 108, "comments": 2, "multi": 2, "blank": 25, "single_comments": 6}, "openlibrary\\scripts\\oclc_to_marc.py": {"loc": 47, "lloc": 27, "sloc": 27, "comments": 2, "multi": 3, "blank": 15, "single_comments": 2}, "openlibrary\\scripts\\oldump.py": {"loc": 42, "lloc": 30, "sloc": 29, "comments": 5, "multi": 0, "blank": 10, "single_comments": 3}, "openlibrary\\scripts\\openlibrary-server": {"loc": 147, "lloc": 77, "sloc": 75, "comments": 6, "multi": 19, "blank": 49, "single_comments": 4}, "openlibrary\\scripts\\open_syllabus_project_parser.py": {"loc": 93, "lloc": 4, "sloc": 3, "comments": 0, "multi": 85, "blank": 5, "single_comments": 0}, "openlibrary\\scripts\\partner_batch_imports.py": {"loc": 311, "lloc": 135, "sloc": 220, "comments": 25, "multi": 28, "blank": 46, "single_comments": 17}, "openlibrary\\scripts\\promise_batch_imports.py": {"loc": 169, "lloc": 83, "sloc": 101, "comments": 3, "multi": 34, "blank": 33, "single_comments": 1}, "openlibrary\\scripts\\pr_slack_digest.py": {"loc": 60, "lloc": 26, "sloc": 53, "comments": 1, "multi": 0, "blank": 6, "single_comments": 1}, "openlibrary\\scripts\\pull-templates.py": {"loc": 105, "lloc": 63, "sloc": 77, "comments": 3, "multi": 2, "blank": 24, "single_comments": 2}, "openlibrary\\scripts\\solr_dump_xisbn.py": {"loc": 188, "lloc": 85, "sloc": 131, "comments": 10, "multi": 22, "blank": 24, "single_comments": 11}, "openlibrary\\scripts\\solr_updater.py": {"loc": 326, "lloc": 181, "sloc": 202, "comments": 36, "multi": 32, "blank": 56, "single_comments": 36}, "openlibrary\\scripts\\sponsor_update_prices.py": {"loc": 60, "lloc": 28, "sloc": 31, "comments": 2, "multi": 18, "blank": 9, "single_comments": 2}, "openlibrary\\scripts\\store_counts.py": {"loc": 16, "lloc": 9, "sloc": 11, "comments": 2, "multi": 0, "blank": 4, "single_comments": 1}, "openlibrary\\scripts\\update-loans.py": {"loc": 39, "lloc": 24, "sloc": 25, "comments": 1, "multi": 4, "blank": 9, "single_comments": 1}, "openlibrary\\scripts\\update_stale_work_references.py": {"loc": 23, "lloc": 14, "sloc": 15, "comments": 0, "multi": 3, "blank": 5, "single_comments": 0}, "openlibrary\\scripts\\upstream-adapter": {"loc": 7, "lloc": 4, "sloc": 4, "comments": 2, "multi": 0, "blank": 2, "single_comments": 1}, "openlibrary\\scripts\\_init_path.py": {"loc": 18, "lloc": 9, "sloc": 8, "comments": 4, "multi": 2, "blank": 4, "single_comments": 4}, "openlibrary\\scripts\\__init__.py": {"loc": 0, "lloc": 0, "sloc": 0, "comments": 0, "multi": 0, "blank": 0, "single_comments": 0}, "openlibrary\\scripts\\gh_scripts\\issue_comment_bot.py": {"loc": 295, "lloc": 127, "sloc": 182, "comments": 27, "multi": 36, "blank": 48, "single_comments": 29}, "openlibrary\\scripts\\providers\\isbndb.py": {"loc": 254, "lloc": 147, "sloc": 176, "comments": 12, "multi": 14, "blank": 48, "single_comments": 16}, "openlibrary\\scripts\\sitemaps\\sitemap.py": {"loc": 228, "lloc": 127, "sloc": 143, "comments": 6, "multi": 26, "blank": 52, "single_comments": 7}, "openlibrary\\scripts\\solr_builder\\setup.py": {"loc": 10, "lloc": 5, "sloc": 9, "comments": 0, "multi": 0, "blank": 1, "single_comments": 0}, "openlibrary\\scripts\\solr_builder\\__init__.py": {"loc": 0, "lloc": 0, "sloc": 0, "comments": 0, "multi": 0, "blank": 0, "single_comments": 0}, "openlibrary\\scripts\\solr_builder\\solr_builder\\fn_to_cli.py": {"loc": 135, "lloc": 89, "sloc": 92, "comments": 5, "multi": 18, "blank": 24, "single_comments": 1}, "openlibrary\\scripts\\solr_builder\\solr_builder\\index_subjects.py": {"loc": 132, "lloc": 52, "sloc": 112, "comments": 4, "multi": 3, "blank": 13, "single_comments": 4}, "openlibrary\\scripts\\solr_builder\\solr_builder\\solr_builder.py": {"loc": 654, "lloc": 292, "sloc": 476, "comments": 17, "multi": 78, "blank": 82, "single_comments": 18}, "openlibrary\\scripts\\solr_builder\\solr_builder\\__init__.py": {"loc": 0, "lloc": 0, "sloc": 0, "comments": 0, "multi": 0, "blank": 0, "single_comments": 0}, "openlibrary\\scripts\\solr_builder\\tests\\test_fn_to_cli.py": {"loc": 71, "lloc": 46, "sloc": 53, "comments": 2, "multi": 5, "blank": 13, "single_comments": 0}, "openlibrary\\scripts\\solr_builder\\tests\\__init__.py": {"loc": 0, "lloc": 0, "sloc": 0, "comments": 0, "multi": 0, "blank": 0, "single_comments": 0}, "openlibrary\\scripts\\tests\\test_affiliate_server.py": {"loc": 120, "lloc": 44, "sloc": 85, "comments": 9, "multi": 17, "blank": 15, "single_comments": 3}, "openlibrary\\scripts\\tests\\test_copydocs.py": {"loc": 93, "lloc": 62, "sloc": 59, "comments": 2, "multi": 16, "blank": 16, "single_comments": 2}, "openlibrary\\scripts\\tests\\test_import_open_textbook_library.py": {"loc": 214, "lloc": 7, "sloc": 212, "comments": 3, "multi": 0, "blank": 2, "single_comments": 0}, "openlibrary\\scripts\\tests\\test_isbndb.py": {"loc": 143, "lloc": 43, "sloc": 112, "comments": 9, "multi": 8, "blank": 17, "single_comments": 6}, "openlibrary\\scripts\\tests\\test_partner_batch_imports.py": {"loc": 132, "lloc": 71, "sloc": 111, "comments": 8, "multi": 0, "blank": 19, "single_comments": 2}, "openlibrary\\scripts\\tests\\test_promise_batch_imports.py": {"loc": 15, "lloc": 5, "sloc": 12, "comments": 0, "multi": 0, "blank": 3, "single_comments": 0}, "openlibrary\\scripts\\tests\\test_solr_updater.py": {"loc": 274, "lloc": 17, "sloc": 264, "comments": 1, "multi": 0, "blank": 9, "single_comments": 1}, "openlibrary\\scripts\\tests\\__init__.py": {"loc": 0, "lloc": 0, "sloc": 0, "comments": 0, "multi": 0, "blank": 0, "single_comments": 0}, "openlibrary\\tests\\test_docker_compose.py": {"loc": 56, "lloc": 34, "sloc": 35, "comments": 2, "multi": 10, "blank": 8, "single_comments": 3}, "openlibrary\\tests\\integration\\test_affiliate_links.py": {"loc": 29, "lloc": 19, "sloc": 23, "comments": 1, "multi": 0, "blank": 5, "single_comments": 1}, "openlibrary\\tests\\integration\\test_auth.py": {"loc": 308, "lloc": 214, "sloc": 226, "comments": 31, "multi": 3, "blank": 48, "single_comments": 31}, "openlibrary\\tests\\integration\\test_landing.py": {"loc": 44, "lloc": 35, "sloc": 35, "comments": 0, "multi": 0, "blank": 9, "single_comments": 0}, "openlibrary\\tests\\integration\\test_loans.py": {"loc": 215, "lloc": 123, "sloc": 179, "comments": 8, "multi": 3, "blank": 25, "single_comments": 8}, "openlibrary\\tests\\integration\\test_microdata.py": {"loc": 26, "lloc": 17, "sloc": 21, "comments": 0, "multi": 0, "blank": 5, "single_comments": 0}, "openlibrary\\tests\\integration\\test_search.py": {"loc": 42, "lloc": 34, "sloc": 34, "comments": 1, "multi": 0, "blank": 7, "single_comments": 1}, "openlibrary\\tests\\integration\\test_sharing.py": {"loc": 123, "lloc": 60, "sloc": 113, "comments": 1, "multi": 0, "blank": 8, "single_comments": 2}, "openlibrary\\tests\\integration\\__init__.py": {"loc": 124, "lloc": 90, "sloc": 106, "comments": 0, "multi": 0, "blank": 18, "single_comments": 0}, "openlibrary\\vendor\\infogami\\sample_run.py": {"loc": 46, "lloc": 25, "sloc": 26, "comments": 5, "multi": 3, "blank": 12, "single_comments": 5}, "openlibrary\\vendor\\infogami\\setup.py": {"loc": 21, "lloc": 2, "sloc": 18, "comments": 1, "multi": 0, "blank": 2, "single_comments": 1}, "openlibrary\\vendor\\infogami\\infogami\\config.py": {"loc": 39, "lloc": 22, "sloc": 20, "comments": 4, "multi": 3, "blank": 14, "single_comments": 2}, "openlibrary\\vendor\\infogami\\infogami\\conftest.py": {"loc": 10, "lloc": 7, "sloc": 6, "comments": 0, "multi": 0, "blank": 4, "single_comments": 0}, "openlibrary\\vendor\\infogami\\infogami\\__init__.py": {"loc": 222, "lloc": 144, "sloc": 137, "comments": 13, "multi": 0, "blank": 65, "single_comments": 20}, "openlibrary\\vendor\\infogami\\infogami\\core\\code.py": {"loc": 475, "lloc": 307, "sloc": 344, "comments": 14, "multi": 16, "blank": 99, "single_comments": 16}, "openlibrary\\vendor\\infogami\\infogami\\core\\db.py": {"loc": 117, "lloc": 75, "sloc": 75, "comments": 3, "multi": 0, "blank": 36, "single_comments": 6}, "openlibrary\\vendor\\infogami\\infogami\\core\\dbupgrade.py": {"loc": 115, "lloc": 82, "sloc": 84, "comments": 1, "multi": 3, "blank": 27, "single_comments": 1}, "openlibrary\\vendor\\infogami\\infogami\\core\\diff.py": {"loc": 58, "lloc": 48, "sloc": 47, "comments": 0, "multi": 0, "blank": 11, "single_comments": 0}, "openlibrary\\vendor\\infogami\\infogami\\core\\forms.py": {"loc": 94, "lloc": 32, "sloc": 79, "comments": 3, "multi": 0, "blank": 15, "single_comments": 0}, "openlibrary\\vendor\\infogami\\infogami\\core\\helpers.py": {"loc": 161, "lloc": 95, "sloc": 89, "comments": 2, "multi": 35, "blank": 35, "single_comments": 2}, "openlibrary\\vendor\\infogami\\infogami\\core\\__init__.py": {"loc": 0, "lloc": 0, "sloc": 0, "comments": 0, "multi": 0, "blank": 0, "single_comments": 0}, "openlibrary\\vendor\\infogami\\infogami\\infobase\\account.py": {"loc": 471, "lloc": 281, "sloc": 344, "comments": 17, "multi": 10, "blank": 94, "single_comments": 23}, "openlibrary\\vendor\\infogami\\infogami\\infobase\\bootstrap.py": {"loc": 289, "lloc": 58, "sloc": 237, "comments": 10, "multi": 2, "blank": 38, "single_comments": 12}, "openlibrary\\vendor\\infogami\\infogami\\infobase\\cache.py": {"loc": 169, "lloc": 87, "sloc": 85, "comments": 0, "multi": 37, "blank": 46, "single_comments": 1}, "openlibrary\\vendor\\infogami\\infogami\\infobase\\client.py": {"loc": 1046, "lloc": 703, "sloc": 742, "comments": 36, "multi": 37, "blank": 220, "single_comments": 47}, "openlibrary\\vendor\\infogami\\infogami\\infobase\\common.py": {"loc": 313, "lloc": 119, "sloc": 199, "comments": 4, "multi": 72, "blank": 40, "single_comments": 2}, "openlibrary\\vendor\\infogami\\infogami\\infobase\\config.py": {"loc": 39, "lloc": 17, "sloc": 16, "comments": 9, "multi": 0, "blank": 13, "single_comments": 10}, "openlibrary\\vendor\\infogami\\infogami\\infobase\\core.py": {"loc": 265, "lloc": 158, "sloc": 154, "comments": 0, "multi": 26, "blank": 74, "single_comments": 11}, "openlibrary\\vendor\\infogami\\infogami\\infobase\\dbstore.py": {"loc": 806, "lloc": 520, "sloc": 626, "comments": 26, "multi": 9, "blank": 138, "single_comments": 33}, "openlibrary\\vendor\\infogami\\infogami\\infobase\\infobase.py": {"loc": 342, "lloc": 189, "sloc": 248, "comments": 11, "multi": 9, "blank": 68, "single_comments": 17}, "openlibrary\\vendor\\infogami\\infogami\\infobase\\logger.py": {"loc": 138, "lloc": 81, "sloc": 92, "comments": 4, "multi": 14, "blank": 27, "single_comments": 5}, "openlibrary\\vendor\\infogami\\infogami\\infobase\\logreader.py": {"loc": 365, "lloc": 206, "sloc": 220, "comments": 7, "multi": 56, "blank": 74, "single_comments": 15}, "openlibrary\\vendor\\infogami\\infogami\\infobase\\lru.py": {"loc": 304, "lloc": 188, "sloc": 178, "comments": 7, "multi": 50, "blank": 63, "single_comments": 13}, "openlibrary\\vendor\\infogami\\infogami\\infobase\\multiple_insert.py": {"loc": 99, "lloc": 63, "sloc": 68, "comments": 4, "multi": 0, "blank": 26, "single_comments": 5}, "openlibrary\\vendor\\infogami\\infogami\\infobase\\readquery.py": {"loc": 286, "lloc": 165, "sloc": 181, "comments": 12, "multi": 43, "blank": 49, "single_comments": 13}, "openlibrary\\vendor\\infogami\\infogami\\infobase\\server.py": {"loc": 756, "lloc": 510, "sloc": 575, "comments": 20, "multi": 5, "blank": 154, "single_comments": 22}, "openlibrary\\vendor\\infogami\\infogami\\infobase\\utils.py": {"loc": 160, "lloc": 72, "sloc": 66, "comments": 0, "multi": 64, "blank": 29, "single_comments": 1}, "openlibrary\\vendor\\infogami\\infogami\\infobase\\writequery.py": {"loc": 533, "lloc": 307, "sloc": 337, "comments": 15, "multi": 92, "blank": 88, "single_comments": 16}, "openlibrary\\vendor\\infogami\\infogami\\infobase\\_json.py": {"loc": 60, "lloc": 30, "sloc": 26, "comments": 0, "multi": 18, "blank": 15, "single_comments": 1}, "openlibrary\\vendor\\infogami\\infogami\\infobase\\__init__.py": {"loc": 51, "lloc": 34, "sloc": 29, "comments": 0, "multi": 3, "blank": 16, "single_comments": 3}, "openlibrary\\vendor\\infogami\\infogami\\infobase\\tests\\pytest_wildcard.py": {"loc": 43, "lloc": 20, "sloc": 17, "comments": 0, "multi": 12, "blank": 14, "single_comments": 0}, "openlibrary\\vendor\\infogami\\infogami\\infobase\\tests\\test_account.py": {"loc": 131, "lloc": 62, "sloc": 94, "comments": 8, "multi": 0, "blank": 28, "single_comments": 9}, "openlibrary\\vendor\\infogami\\infogami\\infobase\\tests\\test_client.py": {"loc": 211, "lloc": 147, "sloc": 158, "comments": 3, "multi": 0, "blank": 50, "single_comments": 3}, "openlibrary\\vendor\\infogami\\infogami\\infobase\\tests\\test_doctests.py": {"loc": 33, "lloc": 13, "sloc": 29, "comments": 0, "multi": 0, "blank": 4, "single_comments": 0}, "openlibrary\\vendor\\infogami\\infogami\\infobase\\tests\\test_infobase.py": {"loc": 241, "lloc": 143, "sloc": 178, "comments": 11, "multi": 4, "blank": 48, "single_comments": 11}, "openlibrary\\vendor\\infogami\\infogami\\infobase\\tests\\test_logreader.py": {"loc": 99, "lloc": 65, "sloc": 69, "comments": 6, "multi": 0, "blank": 24, "single_comments": 6}, "openlibrary\\vendor\\infogami\\infogami\\infobase\\tests\\test_read.py": {"loc": 219, "lloc": 124, "sloc": 168, "comments": 5, "multi": 0, "blank": 47, "single_comments": 4}, "openlibrary\\vendor\\infogami\\infogami\\infobase\\tests\\test_save.py": {"loc": 529, "lloc": 280, "sloc": 420, "comments": 12, "multi": 0, "blank": 96, "single_comments": 13}, "openlibrary\\vendor\\infogami\\infogami\\infobase\\tests\\test_seq.py": {"loc": 28, "lloc": 20, "sloc": 20, "comments": 0, "multi": 0, "blank": 8, "single_comments": 0}, "openlibrary\\vendor\\infogami\\infogami\\infobase\\tests\\test_server.py": {"loc": 0, "lloc": 0, "sloc": 0, "comments": 0, "multi": 0, "blank": 0, "single_comments": 0}, "openlibrary\\vendor\\infogami\\infogami\\infobase\\tests\\test_store.py": {"loc": 226, "lloc": 161, "sloc": 169, "comments": 9, "multi": 0, "blank": 49, "single_comments": 8}, "openlibrary\\vendor\\infogami\\infogami\\infobase\\tests\\test_writequery.py": {"loc": 146, "lloc": 63, "sloc": 125, "comments": 0, "multi": 0, "blank": 21, "single_comments": 0}, "openlibrary\\vendor\\infogami\\infogami\\infobase\\tests\\utils.py": {"loc": 99, "lloc": 59, "sloc": 64, "comments": 4, "multi": 3, "blank": 31, "single_comments": 1}, "openlibrary\\vendor\\infogami\\infogami\\infobase\\tests\\__init__.py": {"loc": 0, "lloc": 0, "sloc": 0, "comments": 0, "multi": 0, "blank": 0, "single_comments": 0}, "openlibrary\\vendor\\infogami\\infogami\\infobase\\_dbstore\\indexer.py": {"loc": 69, "lloc": 28, "sloc": 37, "comments": 2, "multi": 16, "blank": 13, "single_comments": 3}, "openlibrary\\vendor\\infogami\\infogami\\infobase\\_dbstore\\read.py": {"loc": 184, "lloc": 125, "sloc": 142, "comments": 7, "multi": 0, "blank": 33, "single_comments": 9}, "openlibrary\\vendor\\infogami\\infogami\\infobase\\_dbstore\\save.py": {"loc": 605, "lloc": 365, "sloc": 429, "comments": 25, "multi": 26, "blank": 115, "single_comments": 35}, "openlibrary\\vendor\\infogami\\infogami\\infobase\\_dbstore\\schema.py": {"loc": 95, "lloc": 60, "sloc": 62, "comments": 2, "multi": 8, "blank": 23, "single_comments": 2}, "openlibrary\\vendor\\infogami\\infogami\\infobase\\_dbstore\\sequence.py": {"loc": 58, "lloc": 45, "sloc": 49, "comments": 0, "multi": 2, "blank": 7, "single_comments": 0}, "openlibrary\\vendor\\infogami\\infogami\\infobase\\_dbstore\\store.py": {"loc": 243, "lloc": 146, "sloc": 150, "comments": 4, "multi": 29, "blank": 53, "single_comments": 11}, "openlibrary\\vendor\\infogami\\infogami\\infobase\\_dbstore\\__init__.py": {"loc": 2, "lloc": 1, "sloc": 0, "comments": 0, "multi": 2, "blank": 0, "single_comments": 0}, "openlibrary\\vendor\\infogami\\infogami\\plugins\\__init__.py": {"loc": 0, "lloc": 0, "sloc": 0, "comments": 0, "multi": 0, "blank": 0, "single_comments": 0}, "openlibrary\\vendor\\infogami\\infogami\\plugins\\api\\code.py": {"loc": 305, "lloc": 202, "sloc": 222, "comments": 5, "multi": 9, "blank": 68, "single_comments": 6}, "openlibrary\\vendor\\infogami\\infogami\\plugins\\api\\__init__.py": {"loc": 3, "lloc": 1, "sloc": 0, "comments": 0, "multi": 3, "blank": 0, "single_comments": 0}, "openlibrary\\vendor\\infogami\\infogami\\plugins\\i18n\\code.py": {"loc": 99, "lloc": 63, "sloc": 55, "comments": 1, "multi": 15, "blank": 26, "single_comments": 3}, "openlibrary\\vendor\\infogami\\infogami\\plugins\\i18n\\db.py": {"loc": 17, "lloc": 14, "sloc": 13, "comments": 0, "multi": 0, "blank": 4, "single_comments": 0}, "openlibrary\\vendor\\infogami\\infogami\\plugins\\i18n\\__init__.py": {"loc": 3, "lloc": 1, "sloc": 0, "comments": 0, "multi": 3, "blank": 0, "single_comments": 0}, "openlibrary\\vendor\\infogami\\infogami\\plugins\\links\\code.py": {"loc": 20, "lloc": 9, "sloc": 8, "comments": 2, "multi": 6, "blank": 4, "single_comments": 2}, "openlibrary\\vendor\\infogami\\infogami\\plugins\\links\\db.py": {"loc": 27, "lloc": 20, "sloc": 19, "comments": 1, "multi": 0, "blank": 7, "single_comments": 1}, "openlibrary\\vendor\\infogami\\infogami\\plugins\\links\\view.py": {"loc": 91, "lloc": 59, "sloc": 58, "comments": 1, "multi": 0, "blank": 29, "single_comments": 4}, "openlibrary\\vendor\\infogami\\infogami\\plugins\\links\\__init__.py": {"loc": 0, "lloc": 0, "sloc": 0, "comments": 0, "multi": 0, "blank": 0, "single_comments": 0}, "openlibrary\\vendor\\infogami\\infogami\\plugins\\pages\\code.py": {"loc": 300, "lloc": 216, "sloc": 213, "comments": 7, "multi": 21, "blank": 51, "single_comments": 15}, "openlibrary\\vendor\\infogami\\infogami\\plugins\\pages\\__init__.py": {"loc": 3, "lloc": 1, "sloc": 0, "comments": 0, "multi": 3, "blank": 0, "single_comments": 0}, "openlibrary\\vendor\\infogami\\infogami\\plugins\\review\\code.py": {"loc": 87, "lloc": 60, "sloc": 59, "comments": 2, "multi": 5, "blank": 23, "single_comments": 0}, "openlibrary\\vendor\\infogami\\infogami\\plugins\\review\\db.py": {"loc": 66, "lloc": 26, "sloc": 52, "comments": 3, "multi": 0, "blank": 11, "single_comments": 3}, "openlibrary\\vendor\\infogami\\infogami\\plugins\\review\\view.py": {"loc": 88, "lloc": 58, "sloc": 57, "comments": 1, "multi": 0, "blank": 27, "single_comments": 4}, "openlibrary\\vendor\\infogami\\infogami\\plugins\\review\\__init__.py": {"loc": 0, "lloc": 0, "sloc": 0, "comments": 0, "multi": 0, "blank": 0, "single_comments": 0}, "openlibrary\\vendor\\infogami\\infogami\\plugins\\wikitemplates\\code.py": {"loc": 345, "lloc": 236, "sloc": 242, "comments": 4, "multi": 3, "blank": 85, "single_comments": 15}, "openlibrary\\vendor\\infogami\\infogami\\plugins\\wikitemplates\\db.py": {"loc": 26, "lloc": 20, "sloc": 18, "comments": 2, "multi": 0, "blank": 6, "single_comments": 2}, "openlibrary\\vendor\\infogami\\infogami\\plugins\\wikitemplates\\forms.py": {"loc": 21, "lloc": 12, "sloc": 14, "comments": 0, "multi": 0, "blank": 7, "single_comments": 0}, "openlibrary\\vendor\\infogami\\infogami\\plugins\\wikitemplates\\__init__.py": {"loc": 0, "lloc": 0, "sloc": 0, "comments": 0, "multi": 0, "blank": 0, "single_comments": 0}, "openlibrary\\vendor\\infogami\\infogami\\utils\\app.py": {"loc": 354, "lloc": 244, "sloc": 228, "comments": 23, "multi": 22, "blank": 83, "single_comments": 21}, "openlibrary\\vendor\\infogami\\infogami\\utils\\context.py": {"loc": 29, "lloc": 13, "sloc": 11, "comments": 4, "multi": 7, "blank": 7, "single_comments": 4}, "openlibrary\\vendor\\infogami\\infogami\\utils\\delegate.py": {"loc": 230, "lloc": 153, "sloc": 149, "comments": 10, "multi": 3, "blank": 68, "single_comments": 10}, "openlibrary\\vendor\\infogami\\infogami\\utils\\features.py": {"loc": 93, "lloc": 57, "sloc": 53, "comments": 1, "multi": 2, "blank": 34, "single_comments": 4}, "openlibrary\\vendor\\infogami\\infogami\\utils\\flash.py": {"loc": 50, "lloc": 25, "sloc": 28, "comments": 1, "multi": 7, "blank": 14, "single_comments": 1}, "openlibrary\\vendor\\infogami\\infogami\\utils\\i18n.py": {"loc": 220, "lloc": 143, "sloc": 140, "comments": 10, "multi": 16, "blank": 49, "single_comments": 15}, "openlibrary\\vendor\\infogami\\infogami\\utils\\macro.py": {"loc": 146, "lloc": 91, "sloc": 85, "comments": 7, "multi": 7, "blank": 42, "single_comments": 12}, "openlibrary\\vendor\\infogami\\infogami\\utils\\stats.py": {"loc": 59, "lloc": 31, "sloc": 32, "comments": 1, "multi": 7, "blank": 19, "single_comments": 1}, "openlibrary\\vendor\\infogami\\infogami\\utils\\storage.py": {"loc": 124, "lloc": 59, "sloc": 52, "comments": 0, "multi": 43, "blank": 27, "single_comments": 2}, "openlibrary\\vendor\\infogami\\infogami\\utils\\template.py": {"loc": 226, "lloc": 143, "sloc": 142, "comments": 15, "multi": 19, "blank": 54, "single_comments": 11}, "openlibrary\\vendor\\infogami\\infogami\\utils\\types.py": {"loc": 20, "lloc": 12, "sloc": 11, "comments": 0, "multi": 2, "blank": 7, "single_comments": 0}, "openlibrary\\vendor\\infogami\\infogami\\utils\\view.py": {"loc": 517, "lloc": 286, "sloc": 361, "comments": 24, "multi": 14, "blank": 116, "single_comments": 26}, "openlibrary\\vendor\\infogami\\infogami\\utils\\__init__.py": {"loc": 0, "lloc": 0, "sloc": 0, "comments": 0, "multi": 0, "blank": 0, "single_comments": 0}, "openlibrary\\vendor\\infogami\\infogami\\utils\\markdown\\markdown.py": {"loc": 1865, "lloc": 955, "sloc": 1104, "comments": 174, "multi": 178, "blank": 470, "single_comments": 113}, "openlibrary\\vendor\\infogami\\infogami\\utils\\markdown\\mdx_footnotes.py": {"loc": 252, "lloc": 143, "sloc": 141, "comments": 12, "multi": 26, "blank": 75, "single_comments": 10}, "openlibrary\\vendor\\infogami\\infogami\\utils\\markdown\\__init__.py": {"loc": 3, "lloc": 1, "sloc": 0, "comments": 0, "multi": 3, "blank": 0, "single_comments": 0}, "openlibrary\\vendor\\infogami\\infogami\\utils\\tests\\test_app.py": {"loc": 30, "lloc": 18, "sloc": 20, "comments": 3, "multi": 0, "blank": 7, "single_comments": 3}, "openlibrary\\vendor\\infogami\\migration\\migrate-0.4-0.5.py": {"loc": 260, "lloc": 116, "sloc": 191, "comments": 11, "multi": 11, "blank": 47, "single_comments": 11}, "openlibrary\\vendor\\infogami\\scripts\\infobase_server": {"loc": 29, "lloc": 12, "sloc": 10, "comments": 2, "multi": 7, "blank": 11, "single_comments": 1}, "openlibrary\\vendor\\infogami\\scripts\\server": {"loc": 30, "lloc": 12, "sloc": 10, "comments": 2, "multi": 7, "blank": 12, "single_comments": 1}, "openlibrary\\vendor\\infogami\\scripts\\test": {"loc": 72, "lloc": 38, "sloc": 43, "comments": 2, "multi": 5, "blank": 20, "single_comments": 4}, "openlibrary\\vendor\\infogami\\scripts\\_init_path.py": {"loc": 7, "lloc": 5, "sloc": 4, "comments": 0, "multi": 0, "blank": 2, "single_comments": 1}, "openlibrary\\vendor\\infogami\\test\\bug_239238.py": {"loc": 56, "lloc": 29, "sloc": 35, "comments": 0, "multi": 5, "blank": 16, "single_comments": 0}, "openlibrary\\vendor\\infogami\\test\\test_all.py": {"loc": 10, "lloc": 6, "sloc": 6, "comments": 0, "multi": 0, "blank": 4, "single_comments": 0}, "openlibrary\\vendor\\infogami\\test\\test_dbstore.py": {"loc": 177, "lloc": 85, "sloc": 149, "comments": 1, "multi": 0, "blank": 27, "single_comments": 1}, "openlibrary\\vendor\\infogami\\test\\test_doctests.py": {"loc": 17, "lloc": 7, "sloc": 11, "comments": 0, "multi": 2, "blank": 4, "single_comments": 0}, "openlibrary\\vendor\\infogami\\test\\test_infobase.py": {"loc": 358, "lloc": 195, "sloc": 280, "comments": 19, "multi": 0, "blank": 58, "single_comments": 20}, "openlibrary\\vendor\\infogami\\test\\webtest.py": {"loc": 102, "lloc": 68, "sloc": 64, "comments": 1, "multi": 2, "blank": 31, "single_comments": 5}, "openlibrary\\vendor\\infogami\\test\\__init__.py": {"loc": 0, "lloc": 0, "sloc": 0, "comments": 0, "multi": 0, "blank": 0, "single_comments": 0}, "openlibrary\\vendor\\infogami\\tests\\test_doctests.py": {"loc": 37, "lloc": 15, "sloc": 28, "comments": 0, "multi": 0, "blank": 9, "single_comments": 0}, "openlibrary\\vendor\\infogami\\tests\\__init__.py": {"loc": 4, "lloc": 2, "sloc": 2, "comments": 1, "multi": 0, "blank": 1, "single_comments": 1}, "openlibrary\\vendor\\infogami\\tests\\test_infogami\\test_account.py": {"loc": 37, "lloc": 26, "sloc": 28, "comments": 2, "multi": 0, "blank": 7, "single_comments": 2}, "openlibrary\\vendor\\infogami\\tests\\test_infogami\\test_pages.py": {"loc": 87, "lloc": 63, "sloc": 63, "comments": 0, "multi": 0, "blank": 24, "single_comments": 0}, "openlibrary\\vendor\\infogami\\tests\\test_infogami\\__init__.py": {"loc": 54, "lloc": 34, "sloc": 36, "comments": 2, "multi": 0, "blank": 17, "single_comments": 1}, "openlibrary\\vendor\\js\\wmd\\jsmin.py": {"loc": 222, "lloc": 145, "sloc": 146, "comments": 31, "multi": 22, "blank": 24, "single_comments": 30}}
